streamz_zmq/__init__.py
streamz_zmq/sinks.py
streamz_zmq/sources.py
streamz_zmq-0.1.5.dist-info/METADATA
streamz_zmq-0.1.5.dist-info/WHEEL
streamz_zmq-0.1.5.dist-info/licenses/LICENSE
streamz_zmq-0.1.5.dist-info/RECORD
