Metadata-Version: 2.4
Name: streamz-zmq
Version: 0.1.5
Summary: ZeroMQ integration for streamz - high-performance streaming data processing
Project-URL: Homepage, https://github.com/izzet/streamz-zmq
Project-URL: Repository, https://github.com/izzet/streamz-zmq
Project-URL: Documentation, https://github.com/izzet/streamz-zmq#readme
Project-URL: Bug Tracker, https://github.com/izzet/streamz-zmq/issues
Author-email: Izzet Yildirim <izzetcyildirim@gmail.com>
Maintainer-email: Izzet Yildirim <izzetcyildirim@gmail.com>
License: MIT
License-File: LICENSE
Keywords: data-processing,real-time,streaming,zeromq,zmq
Classifier: Development Status :: 4 - Beta
Classifier: Intended Audience :: Developers
Classifier: License :: OSI Approved :: MIT License
Classifier: Programming Language :: Python :: 3
Classifier: Programming Language :: Python :: 3.9
Classifier: Programming Language :: Python :: 3.10
Classifier: Programming Language :: Python :: 3.11
Classifier: Programming Language :: Python :: 3.12
Classifier: Topic :: Software Development :: Libraries :: Python Modules
Classifier: Topic :: System :: Distributed Computing
Classifier: Topic :: System :: Networking
Requires-Python: >3.8
Requires-Dist: pyzmq>=27.0.0
Requires-Dist: streamz>=0.6.4
